tgppuserlocationinfo/__init__.py
tgppuserlocationinfo/__main__.py
tgppuserlocationinfo/main.py
tgppuserlocationinfo/test_main.py
tgppuserlocationinfo-0.1.2.dist-info/METADATA
tgppuserlocationinfo-0.1.2.dist-info/WHEEL
tgppuserlocationinfo-0.1.2.dist-info/entry_points.txt
tgppuserlocationinfo-0.1.2.dist-info/RECORD
