Metadata-Version: 2.4
Name: tgppuserlocationinfo
Version: 0.1.2
Summary: A tool for retrieving and managing user location information based on 3GPP standards
Project-URL: Homepage, https://github.com/fxyzbtc/tgppuserlocationinfo
Project-URL: Repository, https://github.com/fxyzbtc/tgppuserlocationinfo
Project-URL: Bug Tracker, https://github.com/fxyzbtc/tgppuserlocationinfo/issues
Project-URL: Documentation, https://github.com/fxyzbtc/tgppuserlocationinfo#readme
Author-email: fxyzbtc <fxyzbtc@users.noreply.github.com>
License: MIT
Keywords: 3gpp,location,mobile,telecommunications
Classifier: Development Status :: 4 - Beta
Classifier: Environment :: Console
Classifier: Intended Audience :: Developers
Classifier: License :: OSI Approved :: MIT License
Classifier: Programming Language :: Python :: 3.12
Classifier: Topic :: Software Development :: Libraries :: Python Modules
Requires-Python: >=3.12
Requires-Dist: typer>=0.15.2
